setup.py
daktronics/__init__.py
pydak.egg-info/PKG-INFO
pydak.egg-info/SOURCES.txt
pydak.egg-info/dependency_links.txt
pydak.egg-info/requires.txt
pydak.egg-info/top_level.txt