Metadata-Version: 1.0
Name: pydak
Version: 0.2
Summary: Python Library for Daktronics AllSport 5000 Scoring Controllers
Home-page: https://github.com/fimion/pydak
Author: Alex Riviere
Author-email: fimion@gmail.com
License: MIT
Platform: UNKNOWN
